depthai_mock/__init__.py
depthai_mock/cli.py
depthai_mock/pipeline.py
depthai_mock/test.py
depthai_mock/mobilenet-ssd/mobilenet-ssd.blob
depthai_mock/mobilenet-ssd/mobilenet-ssd.json
depthai_mock-0.0.3.dist-info/METADATA
depthai_mock-0.0.3.dist-info/WHEEL
depthai_mock-0.0.3.dist-info/entry_points.txt
depthai_mock-0.0.3.dist-info/top_level.txt
depthai_mock-0.0.3.dist-info/RECORD
