Metadata-Version: 2.1
Name: depthai-mock
Version: 0.0.3
Summary: The tool that allows you to record and playback the DepthAI generated frames
Home-page: https://github.com/luxonis/depthai-mock
Author: Luxonis
Author-email: support@luxonis.com
License: MIT
Project-URL: Bug Tracker, https://github.com/luxonis/depthai-mock/issues
Project-URL: Source Code, https://github.com/luxonis/depthai-mock
Keywords: depthai mock record tool development
Platform: UNKNOWN
Classifier: License :: OSI Approved :: MIT License
Classifier: Programming Language :: Python
Classifier: Programming Language :: Python :: 3
Classifier: Programming Language :: Python :: 3.6
Classifier: Programming Language :: Python :: 3.7
Classifier: Programming Language :: Python :: 3.8
Classifier: Programming Language :: Python :: 3.9
Requires-Dist: depthai (==0.4.1.1)
